backports/tarfile/__init__.py
backports/tarfile/__main__.py
backports/tarfile/compat/__init__.py
backports/tarfile/compat/py38.py
backports.tarfile-1.1.0.dist-info/LICENSE
backports.tarfile-1.1.0.dist-info/METADATA
backports.tarfile-1.1.0.dist-info/WHEEL
backports.tarfile-1.1.0.dist-info/top_level.txt
backports.tarfile-1.1.0.dist-info/RECORD
